{
  "schema_version": 2,
  "pdd_version": "0.0.246.dev96",
  "timestamp_utc": "20260522T012413Z",
  "argv": [
    "contracts",
    "compile",
    "--json",
    "prompts/foo_work_python.prompt"
  ],
  "cwd": "/Users/yifeitao/Desktop/pdd/examples/prompt_lint_contract_e2e_demo",
  "platform": {
    "system": "Darwin",
    "release": "24.6.0",
    "version": "Darwin Kernel Version 24.6.0: Wed Nov  5 21:33:59 PST 2025; root:xnu-11417.140.69.705.2~1/RELEASE_ARM64_T8112",
    "python": "3.13.5 (main, Jun 11 2025, 15:36:57) [Clang 17.0.0 (clang-1700.0.13.3)]"
  },
  "global_options": {
    "force": false,
    "strength": null,
    "temperature": null,
    "time": 0.25,
    "verbose": false,
    "quiet": true,
    "local": false,
    "context": null,
    "output_cost": null,
    "review_examples": false
  },
  "invoked_subcommands": [],
  "total_cost": 0.0,
  "steps": [],
  "errors": [],
  "environment": {
    "PATH": "/Users/yifeitao/Desktop/pdd/.venv/bin:/Users/yifeitao/.antigravity-ide/antigravity-ide/bin:/Users/yifeitao/.antigravity/antigravity/bin:/Users/yifeitao/bin:/Users/yifeitao/.nvm/versions/node/v18.20.8/bin:/Users/yifeitao/.codeium/windsurf/bin:/opt/homebrew/bin:/opt/homebrew/sbin:/Library/Frameworks/Python.framework/Versions/3.11/bin:/usr/local/bin:/System/Cryptexes/App/usr/bin:/usr/bin:/bin:/usr/sbin:/sbin:/var/run/com.apple.security.cryptexd/codex.system/bootstrap/usr/local/bin:/var/run/com.apple.security.cryptexd/codex.system/bootstrap/usr/bin:/var/run/com.apple.security.cryptexd/codex.system/bootstrap/usr/appleinternal/bin:/Library/Apple/usr/bin:/Library/TeX/texbin:/usr/local/go/bin:/Users/yifeitao/.antigravity-ide/antigravity-ide/bin:/Users/yifeitao/.antigravity/antigravity/bin:/Users/yifeitao/bin:/Users/yifeitao/.local/bin:/Users/yifeitao/.nvm/versions/node/v18.20.8/bin:/Users/yifeitao/.codeium/windsurf/bin:/opt/anaconda3/bin:/opt/anaconda3/condabin:/Users/yifeitao/.cursor/extensions/vscjava.vscode-java-debug-0.59.0-universal/bundled/scripts/noConfigScripts:/Users/yifeitao/.cursor/extensions/ms-python.debugpy-2026.6.0-darwin-arm64/bundled/scripts/noConfigScripts",
    "VIRTUAL_ENV": "/Users/yifeitao/Desktop/pdd/.venv",
    "PDD_SKIP_UPDATE_CHECK": "1",
    "PDD_QUIET": "1",
    "PDD_PATH": "/Users/yifeitao/Desktop/pdd/pdd"
  },
  "file_contents": {},
  "terminal_output": "=== STDOUT ===\n[\n  {\n    \"version\": \"pdd.contract_ir.v1\",\n    \"path\": \"prompts/foo_work_python.prompt\",\n    \"has_contract_rules\": true,\n    \"rule_count\": 6,\n    \"error_count\": 0,\n    \"rules\": [\n      {\n        \"id\": \"R1\",\n        \"title\": \"Successful invocation\",\n        \"modal\": \"MUST\",\n        \"condition\": \"parse_bearer_jwt(ctx.authorization).ok == true AND ctx.idempotency_key != '' AND is_active_user(user, ctx.request_received_at) == true AND store.has(ctx.idempotency_key) == false AND (ctx.body_bytes == b'' OR (json.loads(ctx.body_bytes) succeeds AND (amount_cents not present OR amount_cents > 0)))\",\n        \"obligations\": [\n          {\n            \"modal\": \"MUST\",\n            \"type\": \"return\",\n            \"value\": {\n              \"target\": \"HandlerResult with status_code == 200 AND body['result'] == 'ok'\"\n            },\n            \"text\": \"MUST return HandlerResult with status_code == 200 AND body['result'] == 'ok'\"\n          },\n          {\n            \"modal\": \"MUST\",\n            \"type\": \"call\",\n            \"value\": {\n              \"target\": \"store.record(ctx.idempotency_key, request_id) exactly once\"\n            },\n            \"text\": \"MUST call store.record(ctx.idempotency_key, request_id) exactly once\"\n          }\n        ],\n        \"raw\": \"R1 - Successful invocation\\nWhen parse_bearer_jwt(ctx.authorization).ok == true AND ctx.idempotency_key != '' AND is_active_user(user, ctx.request_received_at) == true AND store.has(ctx.idempotency_key) == false AND (ctx.body_bytes == b'' OR (json.loads(ctx.body_bytes) succeeds AND (amount_cents not present OR amount_cents > 0))),\\nthe handler MUST return HandlerResult with status_code == 200 AND body['result'] == 'ok' AND MUST call store.record(ctx.idempotency_key, request_id) exactly once.\"\n      },\n      {\n        \"id\": \"R2\",\n        \"title\": \"Duplicate idempotency key\",\n        \"modal\": \"MUST\",\n        \"condition\": \"store.has(ctx.idempotency_key) is true at\",\n        \"obligations\": [\n          {\n            \"modal\": \"MUST\",\n            \"type\": \"return\",\n            \"value\": {\n              \"target\": \"status_code == 409 with body {'reason':'duplicate','original_request_id': store.get_request_id(ctx.idempotency_key)}\"\n            },\n            \"text\": \"MUST return status_code == 409 with body {'reason':'duplicate','original_request_id': store.get_request_id(ctx.idempotency_key)}\"\n          },\n          {\n            \"modal\": \"MUST NOT\",\n            \"type\": \"call\",\n            \"value\": {\n              \"target\": \"store.record for that key a second time\"\n            },\n            \"text\": \"MUST NOT call store.record for that key a second time\"\n          }\n        ],\n        \"raw\": \"R2 - Duplicate idempotency key\\nWhen store.has(ctx.idempotency_key) is true at the duplicate-check step,\\nthe handler MUST return status_code == 409 with body {'reason':'duplicate','original_request_id': store.get_request_id(ctx.idempotency_key)} AND MUST NOT call store.record for that key a second time.\"\n      },\n      {\n        \"id\": \"R3\",\n        \"title\": \"Authorization gate\",\n        \"modal\": \"MUST\",\n        \"condition\": \"parse_bearer_jwt(ctx.authorization) returns ok=false (missing header, malformed token, exp <= now, or scope lacks 'foo:invoke')\",\n        \"obligations\": [\n          {\n            \"modal\": \"MUST\",\n            \"type\": \"return\",\n            \"value\": {\n              \"target\": \"status_code == 401\"\n            },\n            \"text\": \"MUST return status_code == 401\"\n          },\n          {\n            \"modal\": \"MUST NOT\",\n            \"type\": \"append\",\n            \"value\": {\n              \"target\": \"to AUDIT_LOG\"\n            },\n            \"text\": \"MUST NOT append to AUDIT_LOG\"\n          },\n          {\n            \"modal\": \"MUST NOT\",\n            \"type\": \"call\",\n            \"value\": {\n              \"target\": \"store.record\"\n            },\n            \"text\": \"MUST NOT call store.record\"\n          }\n        ],\n        \"raw\": \"R3 - Authorization gate\\nWhen parse_bearer_jwt(ctx.authorization) returns ok=false (missing header, malformed token, exp <= now, or scope lacks 'foo:invoke'),\\nthe handler MUST return status_code == 401 AND MUST NOT call store.record AND MUST NOT append to AUDIT_LOG.\"\n      },\n      {\n        \"id\": \"R4\",\n        \"title\": \"Inactive user rejection\",\n        \"modal\": \"MUST\",\n        \"condition\": \"is_active_user(user, ctx.request_received_at) is false (after auth and idempotency-key checks pass)\",\n        \"obligations\": [\n          {\n            \"modal\": \"MUST\",\n            \"type\": \"return\",\n            \"value\": {\n              \"target\": \"status_code == 403\"\n            },\n            \"text\": \"MUST return status_code == 403\"\n          },\n          {\n            \"modal\": \"MUST NOT\",\n            \"type\": \"append\",\n            \"value\": {\n              \"target\": \"to AUDIT_LOG\"\n            },\n            \"text\": \"MUST NOT append to AUDIT_LOG\"\n          },\n          {\n            \"modal\": \"MUST NOT\",\n            \"type\": \"call\",\n            \"value\": {\n              \"target\": \"store.record\"\n            },\n            \"text\": \"MUST NOT call store.record\"\n          }\n        ],\n        \"raw\": \"R4 - Inactive user rejection\\nWhen is_active_user(user, ctx.request_received_at) is false (after auth and idempotency-key checks pass),\\nthe handler MUST return status_code == 403 AND MUST NOT call store.record AND MUST NOT append to AUDIT_LOG.\"\n      },\n      {\n        \"id\": \"R5\",\n        \"title\": \"Body validation\",\n        \"modal\": \"MUST\",\n        \"condition\": \"ctx.body_bytes is non-empty and not parseable as JSON\",\n        \"obligations\": [\n          {\n            \"modal\": \"MUST\",\n            \"type\": \"return\",\n            \"value\": {\n              \"target\": \"status_code == 400\"\n            },\n            \"text\": \"MUST return status_code == 400\"\n          },\n          {\n            \"modal\": \"MUST\",\n            \"type\": \"return\",\n            \"value\": {\n              \"target\": \"status_code == 422\"\n            },\n            \"text\": \"MUST return status_code == 422\"\n          }\n        ],\n        \"raw\": \"R5 - Body validation\\nWhen ctx.body_bytes is non-empty and not parseable as JSON, the handler MUST return status_code == 400.\\nWhen the parsed JSON has amount_cents present and amount_cents <= 0, the handler MUST return status_code == 422.\\nIn both cases the handler MUST NOT modify IdempotencyStore entries for any key.\"\n      },\n      {\n        \"id\": \"R6\",\n        \"title\": \"Audit on success\",\n        \"modal\": \"MUST\",\n        \"condition\": \"the handler returns status_code == 200 AND body.get('audit_failed') is not true, it MUST append exactly one entry to AUDIT_LOG containing claims['sub'], request_id, and amount_cents (or null)\",\n        \"obligations\": [\n          {\n            \"modal\": \"MUST\",\n            \"type\": \"append\",\n            \"value\": {\n              \"target\": \"exactly one entry to AUDIT_LOG containing claims['sub'], request_id, and amount_cents (or null)\"\n            },\n            \"text\": \"MUST append exactly one entry to AUDIT_LOG containing claims['sub'], request_id, and amount_cents (or null)\"\n          },\n          {\n            \"modal\": \"MUST NOT\",\n            \"type\": \"append\",\n            \"value\": {\n              \"target\": \"to AUDIT_LOG\"\n            },\n            \"text\": \"MUST NOT append to AUDIT_LOG\"\n          }\n        ],\n        \"raw\": \"R6 - Audit on success\\nWhen the handler returns status_code == 200 AND body.get('audit_failed') is not true, it MUST append exactly one entry to AUDIT_LOG containing claims['sub'], request_id, and amount_cents (or null).\\nWhen the handler returns status_code == 200 AND body['audit_failed'] == true, AUDIT_LOG length MUST be unchanged for this call.\\nWhen the handler returns any status_code != 200, it MUST NOT append to AUDIT_LOG.\"\n      }\n    ],\n    \"compile_errors\": [],\n    \"ir_kind\": \"pdd.contract_ir.v1\"\n  }\n]\n"
}